nubison_model/Model.py
nubison_model/Service.py
nubison_model/Storage.py
nubison_model/__init__.py
nubison_model/utils.py
nubison_model-0.0.8.dist-info/LICENSE
nubison_model-0.0.8.dist-info/METADATA
nubison_model-0.0.8.dist-info/WHEEL
nubison_model-0.0.8.dist-info/RECORD
