Metadata-Version: 2.3
Name: nubison-model
Version: 0.0.8
Summary: 
Author: KyuWoo Choi
Author-email: kyuwoo.choi@gmail.com
Requires-Python: >=3.9,<3.13
Classifier: Programming Language :: Python :: 3
Classifier: Programming Language :: Python :: 3.9
Classifier: Programming Language :: Python :: 3.10
Classifier: Programming Language :: Python :: 3.11
Classifier: Programming Language :: Python :: 3.12
Requires-Dist: PyYAML (>=6.0,<7.0)
Requires-Dist: bentoml (>=1.3.10,<2.0.0)
Requires-Dist: dvc[s3] (>=3.55,<4.0)
Requires-Dist: filelock (>=3.16.1,<4.0.0)
Requires-Dist: mlflow (>=2.17.0,<3.0.0)
